odoo10_addon_product_brand_pos_report-10.0.1.0.2-py3.8-nspkg.pth
odoo/addons/product_brand_pos_report/README.rst
odoo/addons/product_brand_pos_report/__init__.py
odoo/addons/product_brand_pos_report/__manifest__.py
odoo/addons/product_brand_pos_report/i18n/ca.po
odoo/addons/product_brand_pos_report/i18n/es.po
odoo/addons/product_brand_pos_report/i18n/product_brand_pos_report.pot
odoo/addons/product_brand_pos_report/i18n/product_brand_sale_report.pot
odoo/addons/product_brand_pos_report/readme/CONTRIBUTORS.rst
odoo/addons/product_brand_pos_report/readme/DESCRIPTION.rst
odoo/addons/product_brand_pos_report/readme/ROADMAP.rst
odoo/addons/product_brand_pos_report/reports/__init__.py
odoo/addons/product_brand_pos_report/reports/pos_order_report.py
odoo/addons/product_brand_pos_report/reports/pos_order_report_view.xml
odoo/addons/product_brand_pos_report/static/description/icon.png
odoo/addons/product_brand_pos_report/static/description/index.html
odoo10_addon_product_brand_pos_report-10.0.1.0.2.dist-info/METADATA
odoo10_addon_product_brand_pos_report-10.0.1.0.2.dist-info/WHEEL
odoo10_addon_product_brand_pos_report-10.0.1.0.2.dist-info/namespace_packages.txt
odoo10_addon_product_brand_pos_report-10.0.1.0.2.dist-info/top_level.txt
odoo10_addon_product_brand_pos_report-10.0.1.0.2.dist-info/RECORD
