Metadata-Version: 2.1
Name: odoo10-addon-product-brand-pos-report
Version: 10.0.1.0.2
Summary: Product Brand in Point of Sale Report
Home-page: https://github.com/OCA/pos
Author: PlanetaTIC, Odoo Community Association (OCA)
Author-email: support@odoo-community.org
License: AGPL-3
Platform: UNKNOWN
Classifier: Programming Language :: Python
Classifier: Framework :: Odoo
Classifier: Framework :: Odoo :: 10.0
Classifier: License :: OSI Approved :: GNU Affero General Public License v3
Requires-Python: ~=2.7
Requires-Dist: odoo10-addon-product-brand
Requires-Dist: odoo (<10.1dev,>=10.0)
